ai_powered/__init__.py
ai_powered/chat_bot.py
ai_powered/colors.py
ai_powered/constants.py
ai_powered/decorators.py
ai_powered/llm/__init__.py
ai_powered/llm/adapter_selector.py
ai_powered/llm/adapters/chat_adapter.py
ai_powered/llm/adapters/generic_adapter.py
ai_powered/llm/adapters/structured_output_adapter.py
ai_powered/llm/adapters/tools_adapter.py
ai_powered/llm/connection.py
ai_powered/llm/definitions.py
ai_powered/llm/known_models.py
ai_powered/py.typed
ai_powered/schema_deref.py
ai_powered/tool_call.py
ai_powered/tools/google_search.py
ai_powered/utils/function_wraps.py
ai_powered/utils/helpers.py
ai_powered/utils/parse_message.py
ai_powered/utils/safe_eval.py
ai_powered-0.3.1.dist-info/LICENSE
ai_powered-0.3.1.dist-info/METADATA
ai_powered-0.3.1.dist-info/WHEEL
ai_powered-0.3.1.dist-info/RECORD
