Metadata-Version: 2.1
Name: ai-powered
Version: 0.3.1
Summary: The easiest way to develop AI-Powered applications
Home-page: https://github.com/luochen1990/ai_powered
Author: Luo Chen
Author-email: luochen1990@gmail.com
Requires-Python: >=3.10,<4
Classifier: Programming Language :: Python :: 3
Classifier: Programming Language :: Python :: 3.10
Classifier: Programming Language :: Python :: 3.11
Classifier: Programming Language :: Python :: 3.12
Requires-Dist: easy-sync (>=0.2.2,<0.3.0)
Requires-Dist: msgspec (>=0.18.6,<0.19.0)
Requires-Dist: openai (>=1.35.14,<2.0.0)
Project-URL: Repository, https://github.com/luochen1990/ai_powered
